[{"name": "98.5 The Beat - KBBT", "src": "http://65.19.131.164/univision-kbbtfmaac-ibc2?session-id=299623954?t=1526351429"},{"name": "AM1670 Dewberry Jam Radio", "src": "http://s7.viastreaming.net:8835/;?t=1526351430"},{"name": "Inspiration 4 Life Radio", "src": "http://174.36.232.226:8205/stream?t=1526351433"},{"name": "KGSX - KCOR", "src": "http://65.19.131.164/univision-kmyofmaac-ibc2?session-id=1537925175?t=1526351434"},{"name": "KRTU91.7 - KRTU-FM", "src": "http://icy1.abacast.com:80/krtu-krtufmaac-96?t=1526351436"},{"name": "KSYM 90.1 FM", "src": "http://sacrtf2.sac.alamo.edu:8000/stream?t=1526351437"},{"name": "KTSA - KTSA", "src": "http://54.189.181.14/alphasanantonio-ktsaamaac-ibc2?t=1526351439"},{"name": "KXTN 107.5 - KXTN-FM", "src": "http://65.19.131.164/univision-kxtnfmaac-ibc2?session-id=846834868&type=.flv?t=1526351442"},{"name": "Merge98FM", "src": "http://192.240.102.133:11852/1?t=1526351444"},{"name": "NewsTalk 930 AM - KLUP", "src": "http://16693.live.streamtheworld.com/KLUPAMAAC.aac?t=1526351446"}]