[{"name": "Radio Bologna Uno", "src": "http://162.213.121.189:9944/;?t=1526278601"},{"name": "Radio Citta del Capo", "src": "http://stream.rcdc.it:8000/;?t=1526278603"},{"name": "Radio Emilia-Romagna", "src": "http://icecast.aicod.it:8000/radioer_live.mp3?t=1526278606"},{"name": "Radio Fresh", "src": "http://titan.shoutca.st:9161/stream?t=1526278609"},{"name": "Radio Handball Italia", "src": "http://188.165.192.5:8249/;?t=1526278612"},{"name": "Radio International", "src": "http://ice08.fluidstream.net:8080/fluid811.aac?t=1526278614"},{"name": "Radio International Plus", "src": "http://str01.fluidstream.net/fluid1_01.aac?t=1526278617"},{"name": "Radio Italia anni 60", "src": "http://ice12.fluidstream.net/ria60_bo.aac?t=1526278620"},{"name": "Radio Nettuno", "src": "https://eu4.fastcast4u.com/proxy/gpeghe00?mp=/;?t=1526278621"},{"name": "Radio Popolare", "src": "http://livex.radiopopolare.it/radiopop?t=1526278624"}]