[{"name": "EMOOSO", "src": "https://www.radioking.com/play/emooso/177634?t=1526272950"},{"name": "Enjoy 33", "src": "http://radiotrg.ice.infomaniak.ch:80/radiotrg-high?.mp3?t=1526272953"},{"name": "Gold FM", "src": "http://mediam.streamakaci.com/goldfm.mp3?a=b?t=1526272955"},{"name": "La Clé des Ondes 90.1", "src": "http://radio.lacdo.org:80/stream?t=1526272956"},{"name": "Radio Campus Bordeaux", "src": "http://www.radiocampus.fr:8000/campus-bordeaux?t=1526272959"},{"name": "RIG 90.7", "src": "http://163.172.96.134:8004/stream?t=1526272961"},{"name": "Sud Radio", "src": "https://start-sud.ice.infomaniak.ch/start-sud-high.mp3?t=1526272964"},{"name": "Wit 2000", "src": "https://wit2000.ice.infomaniak.ch/wit2000.mp3?t=1526272966"},{"name": "Wit 80's", "src": "https://wit80s.ice.infomaniak.ch/wit80s.mp3?t=1526272968"},{"name": "Wit 90's", "src": "https://wit90s.ice.infomaniak.ch/wit90s.mp3?t=1526272970"},{"name": "Wit @Work", "src": "https://witwork.ice.infomaniak.ch/witwork.mp3?t=1526272972"},{"name": "Wit Club", "src": "https://witclub.ice.infomaniak.ch/witclub.mp3?t=1526272975"},{"name": "Wit Lounge", "src": "https://witlounge.ice.infomaniak.ch/witlounge.mp3?t=1526272976"},{"name": "Youkounkoun Radio Electro", "src": "http://youkounkoun-radio.com:8000/groove.mp3?.mp3?t=1526272979"}]