[{"name": "CRo Brno", "src": "http://icecast2.play.cz:8000/crobrno128.mp3?.mp3?t=1526271845"},{"name": "Hitrádio Magic Brno", "src": "http://ice.abradio.cz/magicbrno64.mp3?t=1526271847"},{"name": "Kiss Hady", "src": "http://icecast1.play.cz/kisshady256.mp3?.mp3?t=1526271849"},{"name": "Radio Proglas", "src": "http://icecast2.play.cz/proglas128?t=1526271850"},{"name": "Radio R", "src": "http://radior.video.muni.cz:8000/FSS_mp3-256.mp3?t=1526271853"},{"name": "Rádio Krokodýl", "src": "http://icecast4.play.cz:80/krokodyl128.mp3?t=1526271854"}]