[{"name": "College Underground Radio", "src": "https://streamer.radio.co/sbc698b4e9/listen?t=1526292167"},{"name": "Jazz 91.9 - WCLK", "src": "http://18093.live.streamtheworld.com/WCLKFM.mp3?t=1526292170"},{"name": "Kdubradio", "src": "https://streaming.radio.co/sc6014ee12/listen?t=1526292173"},{"name": "Kicks 101.5 - WKHX-FM", "src": "http://20833.live.streamtheworld.com/WKHXFMAAC.aac?t=1526292174"},{"name": "La Mejor Atlanta", "src": "http://1.ice1.firststreaming.com:8000/waos_am.aac?t=1526292176"},{"name": "M.A.R.I.A", "src": "http://server12.servistreaming.com:10022/;?t=1526292178"},{"name": "News 95.5 AM 750 WSB - WSB", "src": "http://cmg.streamguys1.com:80/atl750/atl750-sgplayer-aac?t=1526292180"},{"name": "Radio Javan", "src": "https://rj1.rjstream.com/?t=1526292183"},{"name": "WMRE", "src": "http://170.140.196.62:8100/listen?t=1526292185"},{"name": "WRAS (FM)", "src": "http://18893.live.streamtheworld.com:80/WRASFM_SC?t=1526292187"},{"name": "WREK Atlanta 91.1 FM", "src": "http://streaming.wrek.org:8000/main/128kb.mp3?t=1526292189"}]