[{"name": "Akashvani Maitree", "src": "http://radio.mediaisyou.com/live3.mp3?t=1526277523"},{"name": "Chirantanee | BongOnet", "src": "http://radio.bongonet.net:8036/;?t=1526277525"},{"name": "DiscoBani Kolkata | BongOnet", "src": "http://radio.bongonet.net:8008/;?t=1526277527"},{"name": "Folk Nama | BongOnet", "src": "http://radio.bongonet.net:8004/;?t=1526277530"},{"name": "Go Yesteryears | BongOnet", "src": "http://radio.bongonet.net:8016/;?t=1526277531"},{"name": "Radio BongOnet", "src": "http://radio.bongonet.net:8000/;?t=1526277533"},{"name": "Radio City Rabindra Sangeet Radio", "src": "http://prclive1.listenon.in:9300/;?t=1526277536"},{"name": "Radio Hindi International", "src": "http://radio.bongonet.net:8012/;?t=1526277538"},{"name": "Radio Sharanam | BongOnet", "src": "http://radio.bongonet.net:8044/;?t=1526277540"},{"name": "Robichhaya | BongOnet", "src": "http://radio.bongonet.net:8032/;?t=1526277542"}]