[{"name": "AIR Real FM Kozhikode", "src": "http://185.193.112.155:18166/;?t=1526277548"},{"name": "Kerala Malabar Islamic Radio", "src": "http://s4.voscast.com:8068/;?t=1526277551"},{"name": "KICR Kerala Islamic Class Room", "src": "http://50.7.70.66:8786/KICR-SKSSF-Live?t=1526277552"},{"name": "Quran Malayalam Thafseer", "src": "http://37.187.90.196:9484/stream?t=1526277554"},{"name": "Radio Islam", "src": "http://streams.museter.com:8078/;?t=1526277556"},{"name": "Shalom Radio", "src": "https://stream.radio.co/s1383afdc9/low?t=1526277558"},{"name": "SunniOnlineRadio", "src": "http://s7.voscast.com:7812/;?t=1526277560"}]