[{"name": "Oceano FM", "src": "http://sc1.crossdigital.com.br:8170/stream?t=1526268350"},{"name": "Radio Cassino", "src": "http://servidor38.brlogic.com:8182/live?t=1526268352"},{"name": "Radio Marinha FM", "src": "http://sh.upx.com.br:9191/stream.mp3?t=1526268353"},{"name": "Rádio MasQueTal", "src": "http://cast.hoost.com.br:8101/stream?t=1526268356"},{"name": "Rádio Vila Siqueira", "src": "http://streaming24.hstbr.net:8216/live?t=1526268359"},{"name": "Studio Livre FM", "src": "http://74.63.250.83:8236/live?t=1526268360"},{"name": "Web Radio Antena RG", "src": "http://74.63.250.84:8132/live?t=1526268363"}]